egret/__init__.py
egret/common/__init__.py
egret/common/lazy_ptdf_utils.py
egret/common/log.py
egret/common/solver_interface.py
egret/common/tests/__init__.py
egret/common/tests/logging_ext.py
egret/common/tests/test_log.py
egret/data/__init__.py
egret/data/data_utils.py
egret/data/model_data.py
egret/data/networkx_utils.py
egret/data/ptdf_utils.py
egret/data/tests/__init__.py
egret/data/tests/test_model_data.py
egret/model_library/__init__.py
egret/model_library/decl.py
egret/model_library/defn.py
egret/model_library/extensions/gdp_subproblem.py
egret/model_library/extensions/master_bilevel_nk.py
egret/model_library/extensions/subproblem_bilevel_nk.py
egret/model_library/extensions/utils_bilevel_nk.py
egret/model_library/transmission/__init__.py
egret/model_library/transmission/branch.py
egret/model_library/transmission/bus.py
egret/model_library/transmission/gen.py
egret/model_library/transmission/tx_calc.py
egret/model_library/transmission/tx_utils.py
egret/model_library/transmission/tests/test_baseMVA_scaling.py
egret/model_library/transmission/tests/test_tx_utils.py
egret/model_library/unit_commitment/__init__.py
egret/model_library/unit_commitment/fuel_consumption.py
egret/model_library/unit_commitment/fuel_supply.py
egret/model_library/unit_commitment/generation_limits.py
egret/model_library/unit_commitment/non_dispatchable_vars.py
egret/model_library/unit_commitment/objective.py
egret/model_library/unit_commitment/params.py
egret/model_library/unit_commitment/power_balance.py
egret/model_library/unit_commitment/power_vars.py
egret/model_library/unit_commitment/production_costs.py
egret/model_library/unit_commitment/ramping_limits.py
egret/model_library/unit_commitment/reserve_requirement.py
egret/model_library/unit_commitment/reserve_vars.py
egret/model_library/unit_commitment/security_constraints.py
egret/model_library/unit_commitment/services.py
egret/model_library/unit_commitment/startup_costs.py
egret/model_library/unit_commitment/status_vars.py
gridx_egret-0.6.0.dist-info/licenses/LICENSE.txt
gridx_egret-0.6.0.dist-info/METADATA
gridx_egret-0.6.0.dist-info/WHEEL
gridx_egret-0.6.0.dist-info/top_level.txt
gridx_egret-0.6.0.dist-info/RECORD
