Metadata-Version: 2.4
Name: gridx-egret
Version: 0.6.0
Summary: EGRET: Electrical Grid Research and Engineering Tools.
Author: Michael Bynum, Anya Castillo, Bernard Knueven, Jean-Paul Watson
Author-email: Carl Laird <carldlaird@users.noreply.github.com>
Project-URL: homepage, https://github.com/grid-parity-exchange/Egret
Project-URL: source, https://github.com/grid-parity-exchange/Egret
Project-URL: download, https://github.com/grid-parity-exchange/Egret
Project-URL: tracker, https://github.com/grid-parity-exchange/Egret/issues
Requires-Python: <4,>=3.7
License-File: LICENSE.txt
Requires-Dist: pyomo>=6.4
Requires-Dist: numpy
Requires-Dist: pytest
Requires-Dist: pandas
Requires-Dist: matplotlib
Requires-Dist: seaborn
Requires-Dist: scipy
Requires-Dist: networkx
Requires-Dist: coramin==0.1.1
Dynamic: license-file
